eudist.cpython-314t-darwin.so
eudist-0.1.9.dist-info/RECORD
eudist-0.1.9.dist-info/WHEEL
eudist-0.1.9.dist-info/top_level.txt
eudist-0.1.9.dist-info/METADATA
eudist-0.1.9.dist-info/licenses/COPYING
