Metadata-Version: 2.1
Name: eudist
Version: 0.1.9
Summary: Calculate distances between simple shapes such as polygons.
Home-page: https://github.com/dschwoerer/eudist
Author: David Bold
Author-email: dave@ipp.mpg.de
License: GPL
Project-URL: Bug Tracker, https://github.com/dschwoerer/eudist/issues
Classifier: Development Status :: 4 - Beta
Classifier: Intended Audience :: Science/Research
Classifier: Intended Audience :: Education
Classifier: Intended Audience :: Developers
Classifier: License :: OSI Approved :: GNU General Public License v3 or later (GPLv3+)
Classifier: Natural Language :: English
Classifier: Operating System :: POSIX :: Linux
Classifier: Programming Language :: Python :: 3.6
Classifier: Programming Language :: Python :: 3.7
Classifier: Programming Language :: Python :: 3.8
Classifier: Programming Language :: Python :: 3.9
Classifier: Programming Language :: Python :: 3.10
Classifier: Topic :: Scientific/Engineering :: Visualization
License-File: COPYING
Requires-Dist: numpy
Provides-Extra: docs
Requires-Dist: sphinx >=1.4 ; extra == 'docs'
